{"stats":{"minecraft:picked_up":{"minecraft:repeater":22,"minecraft:wind_charge":1720,"minecraft:sticky_piston":2,"minecraft:activator_rail":17,"minecraft:detector_rail":1,"minecraft:redstone_torch":2,"minecraft:scaffolding":8,"minecraft:stone_button":2,"minecraft:redstone":270,"minecraft:lever":16,"minecraft:polished_blackstone_button":1,"minecraft:spruce_sign":1,"minecraft:black_wool":2},"minecraft:killed":{"minecraft:creaking":1,"minecraft:wandering_trader":1,"minecraft:trader_llama":2,"minecraft:villager":21},"minecraft:used":{"minecraft:oak_fence":6,"minecraft:oak_trapdoor":4,"minecraft:moss_block":29,"minecraft:water_bucket":10,"minecraft:chiseled_bookshelf":1,"minecraft:netherite_sword":2,"minecraft:dropper":16,"minecraft:waxed_weathered_copper_bulb":2,"minecraft:redstone_ore":2,"minecraft:armor_stand":2,"minecraft:redstone":2035,"minecraft:dispenser":3,"minecraft:powered_rail":40,"minecraft:lime_wool":155,"minecraft:bone_block":5,"minecraft:oak_sign":2,"minecraft:blue_wool":35,"minecraft:sandstone":989,"minecraft:redstone_block":309,"minecraft:spruce_sign":18,"minecraft:clay":25,"minecraft:debug_stick":3,"minecraft:white_wool":1499,"minecraft:vine":3,"minecraft:diamond_block":4,"minecraft:soul_sand":16,"minecraft:dirt":4,"minecraft:target":152,"minecraft:rail":16,"minecraft:comparator":16,"minecraft:oak_slab":30,"minecraft:tnt":55,"minecraft:spruce_stairs":18,"minecraft:cobblestone_wall":158,"minecraft:jungle_slab":42,"minecraft:orange_wool":109,"minecraft:oak_wood":12,"minecraft:note_block":1213,"minecraft:painting":6,"minecraft:stone_brick_wall":37,"minecraft:cyan_wool":141,"minecraft:obsidian":204,"minecraft:piston":574,"minecraft:oak_log":133,"minecraft:birch_fence":1,"minecraft:redstone_torch":75,"minecraft:sticky_piston":346,"minecraft:glass":141,"minecraft:creaking_spawn_egg":3,"minecraft:black_wool":208,"minecraft:packed_ice":1,"minecraft:lever":221,"minecraft:light":3,"minecraft:honey_block":6,"minecraft:lava_bucket":6,"minecraft:activator_rail":1253,"minecraft:villager_spawn_egg":25,"minecraft:red_wool":83,"minecraft:birch_slab":11,"minecraft:wind_charge":44,"minecraft:iron_block":3,"minecraft:oak_button":1,"minecraft:slime_block":406,"minecraft:stone_button":13,"minecraft:green_wool":166,"minecraft:detector_rail":23,"minecraft:dark_oak_slab":29,"minecraft:pink_wool":63,"minecraft:copper_bulb":20,"minecraft:spruce_hanging_sign":3,"minecraft:bedrock":64,"minecraft:light_gray_wool":2977,"minecraft:repeater":495,"minecraft:glowstone":166,"minecraft:redstone_lamp":33,"minecraft:magenta_wool":159,"minecraft:hay_block":1,"minecraft:emerald_block":15,"minecraft:scaffolding":140,"minecraft:stripped_oak_wood":7,"minecraft:waxed_oxidized_copper_bulb":2,"minecraft:minecart":70,"minecraft:kelp":11,"minecraft:gold_block":142,"minecraft:oak_boat":2,"minecraft:polished_blackstone_button":4,"minecraft:dead_brain_coral_fan":35,"minecraft:white_concrete":5,"minecraft:fire_coral_fan":11,"minecraft:smooth_stone":3,"minecraft:gray_wool":5,"minecraft:observer":1762,"minecraft:pumpkin":1,"minecraft:waxed_copper_bulb":53,"minecraft:horn_coral_fan":9},"minecraft:dropped":{"minecraft:water_bucket":1,"minecraft:villager_spawn_egg":1,"minecraft:lava_bucket":1,"minecraft:stone_button":1,"minecraft:sandstone":1,"minecraft:magenta_wool":1,"minecraft:black_wool":1},"minecraft:custom":{"minecraft:inspect_dropper":20,"minecraft:mob_kills":25,"minecraft:tune_noteblock":6435,"minecraft:leave_game":16,"minecraft:time_since_death":1362165,"minecraft:climb_one_cm":850,"minecraft:time_since_rest":1362195,"minecraft:sprint_one_cm":60159,"minecraft:walk_one_cm":956208,"minecraft:drop":7,"minecraft:damage_dealt":4740,"minecraft:fly_one_cm":14058173,"minecraft:crouch_one_cm":37340,"minecraft:play_time":2132527,"minecraft:deaths":1,"minecraft:sneak_time":93062,"minecraft:walk_under_water_one_cm":3883,"minecraft:boat_one_cm":4745,"minecraft:jump":2695,"minecraft:walk_on_water_one_cm":3461,"minecraft:total_world_time":2264499,"minecraft:inspect_dispenser":7}},"DataVersion":4189}